MANIFEST.in
README.rst
setup.cfg
setup.py
versioneer.py
pymer/__init__.py
pymer/_hash.c
pymer/_hash.pyx
pymer/_version.py
pymer/base.py
pymer/count.py
pymer/markov.py
pymer/tests.py
pymer/xxhash.c
pymer/xxhash.h
pymer.egg-info/PKG-INFO
pymer.egg-info/SOURCES.txt
pymer.egg-info/dependency_links.txt
pymer.egg-info/requires.txt
pymer.egg-info/top_level.txt