Metadata-Version: 1.1
Name: pymer
Version: 0.3.3
Summary: pymer: Pythonic fast k-mer counting routines
Home-page: https://github.com/kdmurray91/pymer
Author: Kevin Murray
Author-email: kdmfoss@gmail.com
License: UNKNOWN
Keywords: kmer
Platform: UNKNOWN
Classifier: Programming Language :: Python
Classifier: Programming Language :: Python :: 2
Classifier: Programming Language :: Python :: 3
Classifier: Development Status :: 3 - Alpha
Classifier: Intended Audience :: Developers
Classifier: Operating System :: OS Independent
Classifier: Topic :: Software Development :: Libraries :: Python Modules
Classifier: Topic :: Scientific/Engineering :: Bio-Informatics
